data_structures/__init__.py
data_structures/array.py
data_structures/linked_lists.py
data_structures/queue.py
data_structures/stack.py
data_structures/trees.py
data_structures_py_jordankbm-0.1.0.dist-info/licenses/LICENSE
data_structures_py_jordankbm-0.1.0.dist-info/METADATA
data_structures_py_jordankbm-0.1.0.dist-info/WHEEL
data_structures_py_jordankbm-0.1.0.dist-info/top_level.txt
data_structures_py_jordankbm-0.1.0.dist-info/RECORD
