Metadata-Version: 2.4
Name: data-structures-py-jordankbm
Version: 0.1.0
Summary: Implementation of various data structures in Python from scratch
Home-page: https://github.com/Jordan-buwa/data-structures-python
Author: Jordan Kevin Buwa Mbouobda
Author-email: jmbouobda@aimsammi.org
License: MIT
Classifier: Programming Language :: Python :: 3
License-File: LICENSE
Requires-Dist: numpy==2.2.4
Requires-Dist: networkx==3.4.2
Requires-Dist: matplotlib==3.10.1
Dynamic: author
Dynamic: author-email
Dynamic: classifier
Dynamic: description
Dynamic: description-content-type
Dynamic: home-page
Dynamic: license
Dynamic: license-file
Dynamic: requires-dist
Dynamic: summary
